segview.py
segview-0.3.0.dist-info/LICENSE.txt
segview-0.3.0.dist-info/METADATA
segview-0.3.0.dist-info/WHEEL
segview-0.3.0.dist-info/top_level.txt
segview-0.3.0.dist-info/RECORD
