Metadata-Version: 2.1
Name: segview
Version: 0.3.0
Summary: A pure Python module for visualising 3D segmentation results
Home-page: https://github.com/yangyushi/segview
Author: Yushi Yang
Author-email: yangyushi1992@icloud.com
License: UNKNOWN
Platform: UNKNOWN
Requires-Python: >=2.7
Requires-Dist: numpy
Requires-Dist: PyOpenGL
Requires-Dist: matplotlib
Requires-Dist: PySide2
Requires-Dist: pyqtgraph
